asyncio_ttl_cache/__init__.py
asyncio_ttl_cache/asyncio_ttl_cache.py
asyncio_ttl_cache-0.0.6.dist-info/WHEEL
asyncio_ttl_cache-0.0.6.dist-info/METADATA
asyncio_ttl_cache-0.0.6.dist-info/RECORD
